{
  "name": "es-calibreweb",
  "lang": "es",
  "intended_use": "webroot",
  "moddir": "",
  "start_url": "books",
  "title": "Calibre-Web: Librero Electrónico",
  "logo_url": "calibreweb.png",
  "description": "Construye tu propia biblioteca comunitaria. Carga libros y documentos para compartir.",
  "extra_description": "Maestros y bibliotecarios puede agregar nuevos libros, organizar colecciones, y borrar libros si el servidor de Internet-in-a-Box se empieza a llenar.",
  "extra_html": "",
  "footnote": "",
  "commit_sha": null
}